odoo/addons/ssi_fixed_asset_disposal/README.rst
odoo/addons/ssi_fixed_asset_disposal/__init__.py
odoo/addons/ssi_fixed_asset_disposal/__manifest__.py
odoo/addons/ssi_fixed_asset_disposal/menu.xml
odoo/addons/ssi_fixed_asset_disposal/data/account_journal_data.xml
odoo/addons/ssi_fixed_asset_disposal/data/account_type_demo.xml
odoo/addons/ssi_fixed_asset_disposal/data/approval_template_data.xml
odoo/addons/ssi_fixed_asset_disposal/data/fixed_asset_depreciation_line_subtype_data.xml
odoo/addons/ssi_fixed_asset_disposal/data/ir_sequence_data.xml
odoo/addons/ssi_fixed_asset_disposal/data/policy_template_data.xml
odoo/addons/ssi_fixed_asset_disposal/data/sequence_template_data.xml
odoo/addons/ssi_fixed_asset_disposal/demo/account_account_demo.xml
odoo/addons/ssi_fixed_asset_disposal/demo/account_journal_demo.xml
odoo/addons/ssi_fixed_asset_disposal/demo/fixed_asset_disposal_type_demo.xml
odoo/addons/ssi_fixed_asset_disposal/i18n/id.po
odoo/addons/ssi_fixed_asset_disposal/i18n/ssi_fixed_asset_disposal.pot
odoo/addons/ssi_fixed_asset_disposal/models/__init__.py
odoo/addons/ssi_fixed_asset_disposal/models/fixed_asset_disposal.py
odoo/addons/ssi_fixed_asset_disposal/models/fixed_asset_disposal_type.py
odoo/addons/ssi_fixed_asset_disposal/security/ir.model.access.csv
odoo/addons/ssi_fixed_asset_disposal/security/ir_module_category_data.xml
odoo/addons/ssi_fixed_asset_disposal/security/ir_rule_data.xml
odoo/addons/ssi_fixed_asset_disposal/security/res_group_data.xml
odoo/addons/ssi_fixed_asset_disposal/static/description/banner.png
odoo/addons/ssi_fixed_asset_disposal/static/description/icon.png
odoo/addons/ssi_fixed_asset_disposal/views/fixed_asset_disposal_type_views.xml
odoo/addons/ssi_fixed_asset_disposal/views/fixed_asset_disposal_views.xml
odoo14_addon_ssi_fixed_asset_disposal-14.0.1.8.0.dist-info/METADATA
odoo14_addon_ssi_fixed_asset_disposal-14.0.1.8.0.dist-info/WHEEL
odoo14_addon_ssi_fixed_asset_disposal-14.0.1.8.0.dist-info/top_level.txt
odoo14_addon_ssi_fixed_asset_disposal-14.0.1.8.0.dist-info/RECORD
